[{"__type__":"cc.Prefab","_name":"MJ_ Group_Top","data":{"__id__":1},"asyncLoadAssets":null},{"__type__":"cc.Node","_name":"MJ_ Group_Top","_children":[{"__id__":2},{"__id__":6},{"__id__":10},{"__id__":14}],"_components":[{"__type__":"cc.Layout","node":{"__id__":1},"_enabled":false,"_layoutSize":{"__type__":"cc.Size","width":118,"height":56},"_resize":1,"_N$layoutType":1,"_N$spacingX":2},{"__type__":"7ff53zmgVJDL64Eox1i+tJS","node":{"__id__":1},"node_card_list":[{"__id__":2},{"__id__":6},{"__id__":10},{"__id__":14}],"imgCardList":[{"__id__":4},{"__id__":8},{"__id__":12},{"__id__":16}],"node_back_list":[{"__id__":5},{"__id__":9},{"__id__":13},{"__id__":17}]}],"_prefab":{"__type__":"cc.PrefabInfo","root":{"__id__":1},"asset":{"__uuid__":"85WUym6HxC1azC/+PEGKrD"},"fileId":"96x6ZEocNLu4/RKg7qklm9"},"_color":{"__type__":"cc.Color","r":167,"g":167,"b":167},"_contentSize":{"__type__":"cc.Size","width":118,"height":56}},{"__type__":"cc.Node","_name":"MJ_Card_Table","_parent":{"__id__":1},"_children":[{"__id__":3},{"__id__":5}],"_components":[{"__type__":"cc.Sprite","node":{"__id__":2},"_spriteFrame":{"__uuid__":"d5TKgSH91Ay6V1AvbX3Vng"}}],"_prefab":{"__type__":"cc.PrefabInfo","root":{"__id__":1},"asset":{"__uuid__":"85WUym6HxC1azC/+PEGKrD"},"fileId":"62P2ByRlpLhpfA/G4kN5GA"},"_contentSize":{"__type__":"cc.Size","width":38,"height":56},"_position":{"__type__":"cc.Vec2","x":-40}},{"__type__":"cc.Node","_name":"img_card","_parent":{"__id__":2},"_components":[{"__id__":4}],"_prefab":{"__type__":"cc.PrefabInfo","root":{"__id__":1},"asset":{"__uuid__":"85WUym6HxC1azC/+PEGKrD"},"fileId":"20Lvx/+SlBwqIcMOJrByiF"},"_contentSize":{"__type__":"cc.Size","width":51,"height":74},"_scaleX":-0.5,"_scaleY":-0.5,"_position":{"__type__":"cc.Vec2","x":0.4,"y":5.7}},{"__type__":"cc.Sprite","node":{"__id__":3},"_spriteFrame":{"__uuid__":"56sOVuX0VAc4Dp5MB7Z2wk"}},{"__type__":"cc.Node","_name":"img_back","_parent":{"__id__":2},"_active":false,"_components":[{"__type__":"cc.Sprite","node":{"__id__":5},"_spriteFrame":{"__uuid__":"70JF9dsZNGBJkcTn5+X8NR"}}],"_prefab":{"__type__":"cc.PrefabInfo","root":{"__id__":1},"asset":{"__uuid__":"85WUym6HxC1azC/+PEGKrD"},"fileId":"b9wgSVsLFNk43a3vHWJrve"},"_contentSize":{"__type__":"cc.Size","width":37,"height":56}},{"__type__":"cc.Node","_name":"MJ_Card_Table","_parent":{"__id__":1},"_children":[{"__id__":7},{"__id__":9}],"_components":[{"__type__":"cc.Sprite","node":{"__id__":6},"_spriteFrame":{"__uuid__":"d5TKgSH91Ay6V1AvbX3Vng"}}],"_prefab":{"__type__":"cc.PrefabInfo","root":{"__id__":1},"asset":{"__uuid__":"85WUym6HxC1azC/+PEGKrD"},"fileId":"f3YgMJ7/tIjK6LAoGt11Iy"},"_contentSize":{"__type__":"cc.Size","width":38,"height":56}},{"__type__":"cc.Node","_name":"img_card","_parent":{"__id__":6},"_components":[{"__id__":8}],"_prefab":{"__type__":"cc.PrefabInfo","root":{"__id__":1},"asset":{"__uuid__":"85WUym6HxC1azC/+PEGKrD"},"fileId":"fakEvSum5A7bQDz/jHFC6W"},"_contentSize":{"__type__":"cc.Size","width":51,"height":74},"_scaleX":-0.5,"_scaleY":-0.5,"_position":{"__type__":"cc.Vec2","x":0.4,"y":5.7}},{"__type__":"cc.Sprite","node":{"__id__":7},"_spriteFrame":{"__uuid__":"56sOVuX0VAc4Dp5MB7Z2wk"}},{"__type__":"cc.Node","_name":"img_back","_parent":{"__id__":6},"_active":false,"_components":[{"__type__":"cc.Sprite","node":{"__id__":9},"_spriteFrame":{"__uuid__":"70JF9dsZNGBJkcTn5+X8NR"}}],"_prefab":{"__type__":"cc.PrefabInfo","root":{"__id__":1},"asset":{"__uuid__":"85WUym6HxC1azC/+PEGKrD"},"fileId":"4592KkDFxC7q8sGGUpzbxQ"},"_contentSize":{"__type__":"cc.Size","width":37,"height":57}},{"__type__":"cc.Node","_name":"MJ_Card_Table","_parent":{"__id__":1},"_children":[{"__id__":11},{"__id__":13}],"_components":[{"__type__":"cc.Sprite","node":{"__id__":10},"_spriteFrame":{"__uuid__":"d5TKgSH91Ay6V1AvbX3Vng"}}],"_prefab":{"__type__":"cc.PrefabInfo","root":{"__id__":1},"asset":{"__uuid__":"85WUym6HxC1azC/+PEGKrD"},"fileId":"20hcIVMOxJY5X+AVugMFMO"},"_contentSize":{"__type__":"cc.Size","width":38,"height":56},"_position":{"__type__":"cc.Vec2","x":40}},{"__type__":"cc.Node","_name":"img_card","_parent":{"__id__":10},"_components":[{"__id__":12}],"_prefab":{"__type__":"cc.PrefabInfo","root":{"__id__":1},"asset":{"__uuid__":"85WUym6HxC1azC/+PEGKrD"},"fileId":"46WJorUSJHj4afcUJW4l/J"},"_contentSize":{"__type__":"cc.Size","width":51,"height":74},"_scaleX":-0.5,"_scaleY":-0.5,"_position":{"__type__":"cc.Vec2","x":0.4,"y":5.7}},{"__type__":"cc.Sprite","node":{"__id__":11},"_spriteFrame":{"__uuid__":"56sOVuX0VAc4Dp5MB7Z2wk"}},{"__type__":"cc.Node","_name":"img_back","_parent":{"__id__":10},"_active":false,"_components":[{"__type__":"cc.Sprite","node":{"__id__":13},"_spriteFrame":{"__uuid__":"70JF9dsZNGBJkcTn5+X8NR"}}],"_prefab":{"__type__":"cc.PrefabInfo","root":{"__id__":1},"asset":{"__uuid__":"85WUym6HxC1azC/+PEGKrD"},"fileId":"7aazQRH11AOYiWYOuytd/a"},"_contentSize":{"__type__":"cc.Size","width":37,"height":57}},{"__type__":"cc.Node","_name":"MJ_Card_Table","_parent":{"__id__":1},"_children":[{"__id__":15},{"__id__":17}],"_components":[{"__type__":"cc.Sprite","node":{"__id__":14},"_spriteFrame":{"__uuid__":"d5TKgSH91Ay6V1AvbX3Vng"}}],"_prefab":{"__type__":"cc.PrefabInfo","root":{"__id__":1},"asset":{"__uuid__":"85WUym6HxC1azC/+PEGKrD"},"fileId":"8b+y/7DwZJnY0uzFIokhdd"},"_contentSize":{"__type__":"cc.Size","width":38,"height":56},"_position":{"__type__":"cc.Vec2","y":13.899999999999999}},{"__type__":"cc.Node","_name":"img_card","_parent":{"__id__":14},"_components":[{"__id__":16}],"_prefab":{"__type__":"cc.PrefabInfo","root":{"__id__":1},"asset":{"__uuid__":"85WUym6HxC1azC/+PEGKrD"},"fileId":"38VnXw+1tAJ71y93PnYf/p"},"_contentSize":{"__type__":"cc.Size","width":51,"height":74},"_scaleX":-0.5,"_scaleY":-0.5,"_position":{"__type__":"cc.Vec2","x":0.4,"y":5.7}},{"__type__":"cc.Sprite","node":{"__id__":15},"_spriteFrame":{"__uuid__":"56sOVuX0VAc4Dp5MB7Z2wk"}},{"__type__":"cc.Node","_name":"img_back","_parent":{"__id__":14},"_components":[{"__type__":"cc.Sprite","node":{"__id__":17},"_spriteFrame":{"__uuid__":"70JF9dsZNGBJkcTn5+X8NR"},"_sizeMode":0}],"_prefab":{"__type__":"cc.PrefabInfo","root":{"__id__":1},"asset":{"__uuid__":"85WUym6HxC1azC/+PEGKrD"},"fileId":"fbzXPpAlBHvphhVIrvHaQk"},"_contentSize":{"__type__":"cc.Size","width":38,"height":56}}]